jaeger_browser/__init__.py
jaeger_browser-1.0.1.dist-info/entry_points.txt
jaeger_browser-1.0.1.dist-info/LICENSE
jaeger_browser-1.0.1.dist-info/WHEEL
jaeger_browser-1.0.1.dist-info/METADATA
jaeger_browser-1.0.1.dist-info/RECORD
