Metadata-Version: 2.1
Name: jaeger_browser
Version: 1.0.1
Summary: Python HTTP server to record traces from the browser.
Home-page: https://github.com/Quansight/jaeger-browser
License: UNKNOWN
Author: Saul Shanabrook
Author-email: saul@quansight.com
Requires-Python: >=3.6
Classifier: License :: OSI Approved :: MIT License
Requires-Dist: jaeger-client
Requires-Dist: uvicorn
Requires-Dist: starlette
Requires-Dist: mypy-extensions
Requires-Dist: typing_extensions
